{
  "version": 1,
  "Pipeline": {
      "producer_conf": { "name" : "SimTelArrayReader", "module": "ctapipe.pipeline.algorithms.simtelarray_reader",
           "class": "SimTelArrayReader","next_steps" : "ListTelsWithData"},
      "consumer_conf": { "name" : "StringWriter", "module": "ctapipe.pipeline.algorithms.string_writer",
                "class": "StringWriter"},
      "stagers_conf" : [{"name": "ListTelsWithData", "class": "ListTelsWithData",
                        "module": "ctapipe.pipeline.algorithms.list_tels_with_data",
                        "next_steps" : "ShuntTelescope", "nb_thread" : 1},
                        {"name": "ShuntTelescope", "class": "ShuntTelescope",
                                          "module": "ctapipe.pipeline.algorithms.shunt_telescope",
                                          "next_steps" : "LSTDump,OtherDump", "nb_thread" : 1},
                        {"name": "LSTDump", "class": "LSTDump",
                                        "module": "ctapipe.pipeline.algorithms.lst_dump",
                                        "next_steps" : "FakeLST", "nb_thread" : 1},
                        {"name": "OtherDump", "class": "OtherDump",
                                        "module": "ctapipe.pipeline.algorithms.other_dump",
                                        "next_steps" : "FakeOther", "nb_thread" : 1},
                        {"name": "FakeLST", "class": "Fake",
                                        "module": "ctapipe.pipeline.algorithms.fake",
                                        "next_steps" : "StringWriter", "nb_thread" : 1},
                        {"name": "FakeOTHER_SUITE", "class": "Fake",
                                        "module": "ctapipe.pipeline.algorithms.fake",
                                        "next_steps" : "StringWriter", "nb_thread" : 1},
                        {"name": "FakeOther", "class": "Fake",
                                        "module": "ctapipe.pipeline.algorithms.fake",
                                            "next_steps" : "FakeOTHER_SUITE", "nb_thread" : 1}
                    ]
  },

  "SimTelArrayReader": { "filename": "gamma_test.simtel.gz"},
  "StringWriter": { "filename": "/tmp/string_writter.txt"}

}
